Metadata-Version: 1.2
Name: SiglentWaterfall
Version: 0.1
Summary: Waterfall Siglent scope traces
Home-page: https://github.com/ewaller/siglentwaterfall
Author: Eric Waller
License: MIT
Platform: UNKNOWN
Classifier: Programming Language :: Python :: 3
Classifier: License :: OSI Approved :: MIT License
Classifier: Operating System :: OS Independent
Requires-Python: >=3.6
